setup.py
FC_CLI.egg-info/PKG-INFO
FC_CLI.egg-info/SOURCES.txt
FC_CLI.egg-info/dependency_links.txt
FC_CLI.egg-info/entry_points.txt
FC_CLI.egg-info/requires.txt
FC_CLI.egg-info/top_level.txt
fc_cli/__init__.py
fc_cli/app.py
fc_cli/config.py