Metadata-Version: 1.0
Name: FC-CLI
Version: 0.0.3
Summary: Get a FullContact report on somebody, and store it in Cloudant
Home-page: https://github.com/garbados/fc_cli
Author: Max Thayer
Author-email: garbados@gmail.com
License: UNKNOWN
Platform: UNKNOWN
